[
  {
    "Colloc": "Le Piano Bar",
    "mdp": "test",
    "": ""
  },
  {
    "Colloc": "Le Gobi",
    "mdp": "test",
    "": ""
  },
  {
    "Colloc": "KT",
    "mdp": "test",
    "": ""
  },
  {
    "Colloc": "Space Mountain",
    "mdp": "test",
    "": ""
  },
  {
    "Colloc": "Uranus",
    "mdp": "test",
    "": ""
  },
  {
    "Colloc": "Bento",
    "mdp": "test",
    "": ""
  },
  {
    "Colloc": "Les Trois Fromages",
    "mdp": "test",
    "": ""
  },
  {
    "Colloc": "Roulotte",
    "mdp": "test",
    "": ""
  },
  {
    "Colloc": "Kame House",
    "mdp": "test",
    "": ""
  },
  {
    "Colloc": "Le Concorde",
    "mdp": "test",
    "": ""
  },
  {
    "Colloc": "Port Picon",
    "mdp": "test",
    "": ""
  },
  {
    "Colloc": "Krolocs",
    "mdp": "test",
    "": ""
  },
  {
    "Colloc": "La Trachee",
    "mdp": "test",
    "": ""
  },
  {
    "Colloc": "Le Donjon",
    "mdp": "test",
    "": ""
  },
  {
    "Colloc": "Le Royaume",
    "mdp": "test",
    "": ""
  },
  {
    "Colloc": "La MAP",
    "mdp": "test",
    "": ""
  },
  {
    "Colloc": "Chez Elmer",
    "mdp": "test",
    "": ""
  },
  {
    "Colloc": "Duplex",
    "mdp": "test",
    "": ""
  },
  {
    "Colloc": "Harem",
    "mdp": "test",
    "": ""
  },
  {
    "Colloc": "Les Extremes",
    "mdp": "test",
    "": ""
  },
  {
    "Colloc": "Le Terminal",
    "mdp": "test",
    "": ""
  },
  {
    "Colloc": "Le Comptoir",
    "mdp": "test",
    "": ""
  },
  {
    "Colloc": "La Niche",
    "mdp": "test",
    "": ""
  },
  {
    "Colloc": "La Glotte",
    "mdp": "test",
    "": ""
  },
  {
    "Colloc": 112,
    "mdp": "test",
    "": ""
  },
  {
    "Colloc": "Corridor",
    "mdp": "test",
    "": ""
  },
  {
    "Colloc": "La Grange Qui Roule",
    "mdp": "test",
    "": ""
  },
  {
    "Colloc": "3M",
    "mdp": "test",
    "": ""
  },
  {
    "Colloc": "Saloon",
    "mdp": "test",
    "": ""
  }
]
